jupyterlab_blockly_polyglot_extension/__init__.py
jupyterlab_blockly_polyglot_extension/_version.py
jupyterlab_blockly_polyglot_extension-1.1.6.data/data/share/jupyter/labextensions/jupyterlab-blockly-polyglot-extension/package.json
jupyterlab_blockly_polyglot_extension-1.1.6.data/data/share/jupyter/labextensions/jupyterlab-blockly-polyglot-extension/schemas/jupyterlab-blockly-polyglot-extension/blockly-polyglot.json
jupyterlab_blockly_polyglot_extension-1.1.6.data/data/share/jupyter/labextensions/jupyterlab-blockly-polyglot-extension/schemas/jupyterlab-blockly-polyglot-extension/package.json.orig
jupyterlab_blockly_polyglot_extension-1.1.6.data/data/share/jupyter/labextensions/jupyterlab-blockly-polyglot-extension/static/0.f3c328f64fe520a87fcf.js
jupyterlab_blockly_polyglot_extension-1.1.6.data/data/share/jupyter/labextensions/jupyterlab-blockly-polyglot-extension/static/176.f741de3781ec1cbecbb0.js
jupyterlab_blockly_polyglot_extension-1.1.6.data/data/share/jupyter/labextensions/jupyterlab-blockly-polyglot-extension/static/176.f741de3781ec1cbecbb0.js.LICENSE.txt
jupyterlab_blockly_polyglot_extension-1.1.6.data/data/share/jupyter/labextensions/jupyterlab-blockly-polyglot-extension/static/210.10e73b900935112fe54d.js
jupyterlab_blockly_polyglot_extension-1.1.6.data/data/share/jupyter/labextensions/jupyterlab-blockly-polyglot-extension/static/247.deb438e47e46060dc2b5.js
jupyterlab_blockly_polyglot_extension-1.1.6.data/data/share/jupyter/labextensions/jupyterlab-blockly-polyglot-extension/static/346.41c67e2c877d6fff24bf.js
jupyterlab_blockly_polyglot_extension-1.1.6.data/data/share/jupyter/labextensions/jupyterlab-blockly-polyglot-extension/static/396.9a8c65bf38dbde81a50b.js
jupyterlab_blockly_polyglot_extension-1.1.6.data/data/share/jupyter/labextensions/jupyterlab-blockly-polyglot-extension/static/396.9a8c65bf38dbde81a50b.js.LICENSE.txt
jupyterlab_blockly_polyglot_extension-1.1.6.dist-info/METADATA
jupyterlab_blockly_polyglot_extension-1.1.6.dist-info/WHEEL
jupyterlab_blockly_polyglot_extension-1.1.6.dist-info/licenses/LICENSE
jupyterlab_blockly_polyglot_extension-1.1.6.dist-info/RECORD
