Metadata-Version: 2.4
Name: jupyterlab_blockly_polyglot_extension
Version: 1.1.6
Summary: A JupyterLab extension implementing a Blockly palette for multiple programming languages.
Project-URL: Homepage, https://github.com/aolney/jupyterlab-blockly-polyglot-extension
Project-URL: Bug Tracker, https://github.com/aolney/jupyterlab-blockly-polyglot-extension/issues
Project-URL: Repository, https://github.com/aolney/jupyterlab-blockly-polyglot-extension.git
Author-email: Andrew Olney <aolney@memphis.edu>
License:                                  Apache License
License-File: LICENSE
Keywords: jupyter,jupyterlab,jupyterlab-extension
Classifier: Framework :: Jupyter
Classifier: Framework :: Jupyter :: JupyterLab
Classifier: Framework :: Jupyter :: JupyterLab :: 4
Classifier: Framework :: Jupyter :: JupyterLab :: Extensions
Classifier: Framework :: Jupyter :: JupyterLab :: Extensions :: Prebuilt
Classifier: License :: OSI Approved :: BSD License
Classifier: Programming Language :: Python
Classifier: Programming Language :: Python :: 3
Classifier: Programming Language :: Python :: 3.9
Classifier: Programming Language :: Python :: 3.10
Classifier: Programming Language :: Python :: 3.11
Classifier: Programming Language :: Python :: 3.12
Classifier: Programming Language :: Python :: 3.13
Requires-Python: >=3.9
